pyscaffoldext/custom_extension/__init__.py
pyscaffoldext/custom_extension/extension.py
pyscaffoldext/custom_extension/templates/__init__.py
pyscaffoldext/custom_extension/templates/conftest.template
pyscaffoldext/custom_extension/templates/contributing.template
pyscaffoldext/custom_extension/templates/extension.template
pyscaffoldext/custom_extension/templates/helpers.template
pyscaffoldext/custom_extension/templates/publish_package.template
pyscaffoldext/custom_extension/templates/readme.template
pyscaffoldext/custom_extension/templates/test_custom_extension.template
pyscaffoldext_custom_extension-0.6.3.dist-info/AUTHORS.rst
pyscaffoldext_custom_extension-0.6.3.dist-info/LICENSE.txt
pyscaffoldext_custom_extension-0.6.3.dist-info/METADATA
pyscaffoldext_custom_extension-0.6.3.dist-info/WHEEL
pyscaffoldext_custom_extension-0.6.3.dist-info/entry_points.txt
pyscaffoldext_custom_extension-0.6.3.dist-info/top_level.txt
pyscaffoldext_custom_extension-0.6.3.dist-info/RECORD
