Metadata-Version: 2.1
Name: pyscaffoldext-custom-extension
Version: 0.6.3
Summary: PyScaffold extension to create a custom PyScaffold extension
Home-page: https://github.com/pyscaffold/pyscaffoldext-custom-extension
Author: Simone Robutti
Author-email: simone.robutti@teraki.com
License: MIT
Project-URL: Documentation, https://pyscaffoldext-custom-extension.readthedocs.io/
Project-URL: Source, https://github.com/pyscaffold/pyscaffoldext-custom-extension/
Project-URL: Tracker, https://github.com/pyscaffold/pyscaffoldext-custom-extension/issues
Project-URL: Download, https://pypi.org/project/pyscaffoldext-custom-extension/#files
Project-URL: Twitter, https://twitter.com/PyScaffold
Platform: any
Classifier: Development Status :: 4 - Beta
Classifier: Topic :: Utilities
Classifier: Programming Language :: Python
Classifier: Programming Language :: Python :: 3
Classifier: Programming Language :: Python :: 3 :: Only
Classifier: Environment :: Console
Classifier: Intended Audience :: Developers
Classifier: License :: OSI Approved :: MIT License
Classifier: Operating System :: POSIX :: Linux
Classifier: Operating System :: Unix
Classifier: Operating System :: MacOS
Classifier: Operating System :: Microsoft :: Windows
License-File: LICENSE.txt
License-File: AUTHORS.rst
Requires-Dist: pyscaffold (<5.0a0,>=4.0.1)
Requires-Dist: configupdater (<4,>=2.0)
Requires-Dist: packaging (>=20.7)
Requires-Dist: importlib-metadata ; python_version < "3.8"
Provides-Extra: testing
Requires-Dist: tox ; extra == 'testing'
Requires-Dist: pre-commit ; extra == 'testing'
Requires-Dist: setuptools-scm ; extra == 'testing'
Requires-Dist: virtualenv ; extra == 'testing'
Requires-Dist: configupdater ; extra == 'testing'
Requires-Dist: pytest ; extra == 'testing'
Requires-Dist: pytest-cov ; extra == 'testing'
Requires-Dist: pytest-xdist ; extra == 'testing'
